cursofiap/__init__.py
cursofiap/core.py
mansufa_api_package-1.0.0.dist-info/METADATA
mansufa_api_package-1.0.0.dist-info/WHEEL
mansufa_api_package-1.0.0.dist-info/top_level.txt
mansufa_api_package-1.0.0.dist-info/RECORD
