Metadata-Version: 2.4
Name: mansufa_api-package
Version: 1.0.0
Summary: Descricao da sua lib cursofiap
Author: Fellipe Pinho
Author-email: fellipemrpinho@gmail.com
License: MIT
Dynamic: author
Dynamic: author-email
Dynamic: description
Dynamic: description-content-type
Dynamic: license
Dynamic: summary
